quickchat_sdk/__init__.py
quickchat_sdk/account.py
quickchat_sdk/connection.py
quickchat_sdk/message.py
quickchat_sdk-0.1.1.dist-info/licenses/LICENSE
quickchat_sdk-0.1.1.dist-info/METADATA
quickchat_sdk-0.1.1.dist-info/WHEEL
quickchat_sdk-0.1.1.dist-info/top_level.txt
quickchat_sdk-0.1.1.dist-info/RECORD
