Metadata-Version: 2.4
Name: quickchat_sdk
Version: 0.1.1
Summary: A simple SDK for interfacing with the Quick Chat chatting platform.
Home-page: https://github.com/qc1159/quickchat-python-sdk
Author: GoofyMooCow
License: MIT
Classifier: Programming Language :: Python :: 3
Classifier: License :: OSI Approved :: MIT License
Classifier: Operating System :: OS Independent
Requires-Python: >=3.6
License-File: LICENSE
Requires-Dist: requests
Requires-Dist: websocket-client
Dynamic: author
Dynamic: classifier
Dynamic: description
Dynamic: description-content-type
Dynamic: home-page
Dynamic: license
Dynamic: license-file
Dynamic: requires-dist
Dynamic: requires-python
Dynamic: summary
